{
  "schema_version": 2,
  "kind": "interval_witness",
  "name": "nontrivial_snarks_n28_0225",
  "graph": {
    "n": 28,
    "m": 42,
    "graph6": "[?GW?e??GCCAa???g_@A?CG???y?A??GC?P????[????O?@O????A?A_@?A????L",
    "edges": [
      [
        0,
        8
      ],
      [
        0,
        12
      ],
      [
        0,
        22
      ],
      [
        1,
        14
      ],
      [
        1,
        18
      ],
      [
        1,
        24
      ],
      [
        2,
        4
      ],
      [
        2,
        11
      ],
      [
        2,
        15
      ],
      [
        3,
        5
      ],
      [
        3,
        7
      ],
      [
        3,
        16
      ],
      [
        4,
        5
      ],
      [
        4,
        12
      ],
      [
        5,
        14
      ],
      [
        6,
        7
      ],
      [
        6,
        10
      ],
      [
        6,
        23
      ],
      [
        7,
        15
      ],
      [
        8,
        9
      ],
      [
        8,
        16
      ],
      [
        9,
        11
      ],
      [
        9,
        20
      ],
      [
        10,
        25
      ],
      [
        10,
        26
      ],
      [
        11,
        19
      ],
      [
        12,
        13
      ],
      [
        13,
        18
      ],
      [
        13,
        20
      ],
      [
        14,
        17
      ],
      [
        15,
        17
      ],
      [
        16,
        17
      ],
      [
        18,
        19
      ],
      [
        19,
        21
      ],
      [
        20,
        21
      ],
      [
        21,
        26
      ],
      [
        22,
        23
      ],
      [
        22,
        25
      ],
      [
        23,
        27
      ],
      [
        24,
        25
      ],
      [
        24,
        27
      ],
      [
        26,
        27
      ]
    ],
    "orientation": "lex (u,v) with u<v points u->v"
  },
  "pinning": {
    "pinned_vertex": 0,
    "pinned_edge_indices": [
      0,
      1,
      2
    ],
    "pinned_signs": [
      1,
      1,
      1
    ],
    "target_labels": [
      "(1,0,0)",
      "(-1/2, s/2, 0)",
      "(-1/2, -s/2, 0)"
    ],
    "dropped_redundant_vertex": 27
  },
  "system": {
    "free_vars": [
      "x_3_0",
      "x_3_1",
      "x_3_2",
      "x_4_0",
      "x_4_1",
      "x_4_2",
      "x_5_0",
      "x_5_1",
      "x_5_2",
      "x_6_0",
      "x_6_1",
      "x_6_2",
      "x_7_0",
      "x_7_1",
      "x_7_2",
      "x_8_0",
      "x_8_1",
      "x_8_2",
      "x_9_0",
      "x_9_1",
      "x_9_2",
      "x_10_0",
      "x_10_1",
      "x_10_2",
      "x_11_0",
      "x_11_1",
      "x_11_2",
      "x_12_0",
      "x_12_1",
      "x_12_2",
      "x_13_0",
      "x_13_1",
      "x_13_2",
      "x_14_0",
      "x_14_1",
      "x_14_2",
      "x_15_0",
      "x_15_1",
      "x_15_2",
      "x_16_0",
      "x_16_1",
      "x_16_2",
      "x_17_0",
      "x_17_1",
      "x_17_2",
      "x_18_0",
      "x_18_1",
      "x_18_2",
      "x_19_0",
      "x_19_1",
      "x_19_2",
      "x_20_0",
      "x_20_1",
      "x_20_2",
      "x_21_0",
      "x_21_1",
      "x_21_2",
      "x_22_0",
      "x_22_1",
      "x_22_2",
      "x_23_0",
      "x_23_1",
      "x_23_2",
      "x_24_0",
      "x_24_1",
      "x_24_2",
      "x_25_0",
      "x_25_1",
      "x_25_2",
      "x_26_0",
      "x_26_1",
      "x_26_2",
      "x_27_0",
      "x_27_1",
      "x_27_2",
      "x_28_0",
      "x_28_1",
      "x_28_2",
      "x_29_0",
      "x_29_1",
      "x_29_2",
      "x_30_0",
      "x_30_1",
      "x_30_2",
      "x_31_0",
      "x_31_1",
      "x_31_2",
      "x_32_0",
      "x_32_1",
      "x_32_2",
      "x_33_0",
      "x_33_1",
      "x_33_2",
      "x_34_0",
      "x_34_1",
      "x_34_2",
      "x_35_0",
      "x_35_1",
      "x_35_2",
      "x_36_0",
      "x_36_1",
      "x_36_2",
      "x_37_0",
      "x_37_1",
      "x_37_2",
      "x_38_0",
      "x_38_1",
      "x_38_2",
      "x_39_0",
      "x_39_1",
      "x_39_2",
      "x_40_0",
      "x_40_1",
      "x_40_2",
      "x_41_0",
      "x_41_1",
      "x_41_2",
      "s"
    ],
    "n_free_vars": 118,
    "n_polynomials": 118,
    "polynomial_hash_sha256": "227d897b555cf8a37b93209b7c3b5987793c2fd817e851b1df8a6bf7f9a65188",
    "polynomial_hash_canonicalization": "sympy.expand then sympy.srepr per poly, joined"
  },
  "krawczyk": {
    "radius_decimal": "1e-05",
    "dps": 50,
    "center_decimal": [
      "-0.73164242907444403440399146204701592034394209083489",
      "0.17503588366699607158478378254029330480654088707480",
      "-0.65883366292787510277676331087528260101913722266722",
      "0.41110686190542808006221795055258396175937368037888",
      "-0.90956200923505006040459262806915632214376653051840",
      "0.060729724604760024379505774847153365359472854466000",
      "0.32053556716901595434177351149443195858456841045601",
      "0.73452612556805398881980884552886301733722564344360",
      "0.59810393832311507839725753602812923565966436820122",
      "-0.037323537872255639096070821225462094380245375385376",
      "-0.18888167237439740641486774949376513565703435295340",
      "0.98129030738194346980459202881985525711275591435966",
      "-0.26017135049284690600160909130333002983327336122069",
      "0.90147486085724464832774112779592168678584776192413",
      "-0.34591031153340833963776562569351700604290421014420",
      "0.29749488836510254509767991252879212421351873660607",
      "-0.71259318848284724191287337830215655112881340897072",
      "-0.63537999584853513016682640312633825106985170421547",
      "0.77795872053246506397035167875872816907579881835023",
      "0.38580599011477681299034636304676516746726068597944",
      "0.49591729868905224200987394136199142229318199234339",
      "-0.90315261613911758723693632460961604905051904322722",
      "-0.025686888177651198795701511690245358454700190168187",
      "0.42855050546792797052913683635336158127520730958267",
      "0.12519389560665252326658464585088787997472022487699",
      "-0.36011910193712561419464485135651980901256049581126",
      "-0.92446780415698021253901077771535300356838930192607",
      "-0.88399720844536941636845074197124504926891463611069",
      "-0.10035867480592740745372748723420197014381910624076",
      "0.45659289509583064257024417834463042488192839813875",
      "0.84667367057311377727237992074578295488866926072532",
      "-0.088522997568469998961140262259563165513215246712645",
      "0.52469741228611282723434785047522483223082751622091",
      "-0.10603848791290435239809906321251688019311581776046",
      "0.28544731530884940553661887581256319732344157973869",
      "0.95251019378488288458011811970662184717511039048214",
      "0.81814474915471090567476229148946884539933799033951",
      "-0.17782741817624847728319394407114339475638551714941",
      "0.54682408393865098805354657688083455253265775540155",
      "0.058095546045427727503613379701341839960032190651651",
      "0.0092996863056085647044029665135856355971612626235966",
      "-0.99826771127002843838579180283168728540431501382656",
      "-0.87624029520013863317837567119081068535937018099117",
      "0.16852773187063991257879097755755775915922425452582",
      "0.45144362733137745033224522595085273287165725842501",
      "-0.085007866984406681562174033120147203651181052887703",
      "-0.20351430635389967607889545576138875321108570731760",
      "0.97537458940657895858268341323419613380786506498422",
      "0.50000000000000000000000000000000000000000000000000",
      "-0.81574339779802705506501102706720861122247714528609",
      "-0.29079667974192860231979895877615587467440277334239",
      "0.50000000000000000000000000000000000000000000000000",
      "0.81574339779802705506501102706720861122247714528609",
      "0.29079667974192860231979895877615587467440277334239",
      "0.93069626119602846036996124817558095299811014407640",
      "-0.15977941755274236197028342527665294521259491434534",
      "0.32905167849783166655476441753482668994745206136404",
      "-0.43069626119602846036996124817558095299811014407640",
      "-0.65596398024528469309472760179055566600988223094076",
      "-0.61984835823976026887456337631098256462185483470643",
      "0.55400885499955362054577519854707791683884779615499",
      "-0.68370559445327510309167299423315088278105466894182",
      "-0.47499563018556001019563394368282261229278963567485",
      "-0.49591330895412589304216181884573607687881560550334",
      "0.69300528075888366779607596074673651837821593156542",
      "-0.52327208108446842819015785914886467311152537815171",
      "0.67052491070318155436835215687225092316483678285571",
      "0.74169544330450228635745770251926874157325284757879",
      "-0.016858633035576673083001208158690316095452148780158",
      "0.34667367057311377727237992074578295488866926072532",
      "0.77750240621596864780258290849337301795818738019255",
      "0.52469741228611282723434785047522483223082751622091",
      "-0.52974687305007514968834508608491900293053473886304",
      "0.36150657883523490804210247251254204627493092599692",
      "0.76725565749136816091844514147630186663697817532743",
      "0.87642054362318892696072500683070195781920399958836",
      "0.41599582738073373976048043598083097168325645419563",
      "-0.24255824520525533368409729100107703440615065910652",
      "-0.83768091698734838680209052525953280053705790859536",
      "0.46048319897584547712140265835285650212998246681349",
      "0.29367653085700778180335480883133924615597316781493",
      "0.21248702138069586353550587940864492056233768371837",
      "-0.91610749483674691799176883406354530433989911628833",
      "0.33999459355804382841585701010785788273801336076875",
      "0.62519389560665252326658464585088787997472022487699",
      "0.45562429586090144087036617571068880220991664947484",
      "-0.63367112441505161021921181893919712889398652858368",
      "-0.11864001114464706962612713553233504117116105848416",
      "-0.54805543039981515236249015555661427586883560452148",
      "0.82798538209612818529795091632345523199645102979343",
      "0.55188489955853448474222502133991588199367572437154",
      "0.19364001290468713399496754696265446570441724305732",
      "0.81112674906055151221494970816476491590099888101328",
      "0.44572428242716046659076375865512100482109385551195",
      "-0.23996815286455095333424716580972469432662577674513",
      "-0.86240660344501560255866066731205959902800549381295",
      "0.99760918198569495133298877999503688681476957988350",
      "-0.046328139959863819339279618847070228622208533687816",
      "-0.051279854384464090343710959147294683127006612799670",
      "0.044257681710670542904624722888214491096054056388635",
      "-0.60290245363899017935529837892693448442874954329384",
      "-0.79658639770315076323845374619657540801761814365588",
      "-0.54425768171067054290462472288821449109605405638864",
      "-0.26312295014544846740842479182600169904265308361135",
      "0.79658639770315076323845374619657540801761814365588",
      "-0.83198261348946809027375094830259619426331612460253",
      "-0.43437472176835026677650740136937672526952528876802",
      "-0.34514277037177331290620852024572267514596088523087",
      "-0.0097511732888830776411504756588634257427937397663516",
      "0.94682854459872357050009778605915258182370775255317",
      "-0.32159076751759075304281980251375279572482850798103",
      "0.33028674045789903198292398715329538432736215022236",
      "-0.21230241903066958168028894053028956448648210910958",
      "0.91969470584070583144007733854188203138449287618225",
      "0.50169587303156905829082696114930080993595397438016",
      "0.64667714079901984845679634189966628975600739787760",
      "-0.57455193546893251853386881829615935623853199095138",
      "1.7320508075688772935274463415058723669428052538104"
    ],
    "F_residual_at_center_decimal": "2.67276471009219564614053646715e-51",
    "containment_margins_lo_decimal": [
      "0.00000999243506262765675670627944816",
      "0.00000999459588489744174214350973536",
      "0.00000999022966941264804931800066641",
      "0.00000999577109549066259067988881324",
      "0.00000999848181037315688202311848722",
      "0.00000998535407396925329226796984757",
      "0.00000999535487620272129987200232439",
      "0.00000999442875558030770310231424826",
      "0.00000999509681120853336036396364242",
      "0.00000998799912686460467152298697949",
      "0.00000999257354576377857398361542275",
      "0.00000999794330169861528894529060230",
      "0.00000998788872316573337318622311471",
      "0.00000999509091777410622118380936568",
      "0.00000999434523858185992137557653064",
      "0.00000999607797118544081656105023429",
      "0.00000999549298220093621311741779040",
      "0.00000999530750348028723680827229547",
      "0.00000999215547760601954699979253682",
      "0.00000999374868604348588122741867528",
      "0.00000999021756744003800746604436440",
      "0.00000999645735280678346210720116315",
      "0.00000998440572909602240809009524186",
      "0.00000999248149129987819728969534563",
      "0.00000998930699743322823341413720311",
      "0.00000998759348818888445341791691587",
      "0.00000999607014256946129503287601458",
      "0.00000999428242690610263680254054229",
      "0.00000999437428110783531661004835260",
      "0.00000998840251491981811785971711925",
      "0.00000999336007695975009614970150027",
      "0.00000999608388715172084983210155382",
      "0.00000999037569764779261024776324330",
      "0.00000998695596743616600611398496791",
      "0.00000999292234306896453745667789955",
      "0.00000999704816220635727241777172445",
      "0.00000999620657817500772288220973804",
      "0.00000998786177817938431104344237576",
      "0.00000999259909821720620728893017688",
      "0.00000999200536521961939632119621056",
      "0.00000998808069976488918703308639969",
      "0.00000999929389249406780749955469226",
      "0.00000999545058435058204099954625378",
      "0.00000999637962954144195615036874409",
      "0.00000999196809577836545532502736311",
      "0.00000999287349256884004104060916769",
      "0.00000999372764825789003082285706272",
      "0.00000999834731055650166082097608901",
      "0.00000999940000000000000000000000000",
      "0.00000999391618750035103228845886569",
      "0.00000998293367763196578837145624383",
      "0.00000999940000000000000000000000000",
      "0.00000999391618750035103228845886569",
      "0.00000998293367763196578837145624383",
      "0.00000999610224255593294807470798795",
      "0.00000998788365583224381758382711287",
      "0.00000999294551304867523536926409863",
      "0.00000999647378501386151915096516157",
      "0.00000998201072529722616832325010030",
      "0.00000997970315352180336905106826654",
      "0.00000999247608509710058330162481412",
      "0.00000999638467536286425937383421724",
      "0.00000998724856323852428366783297175",
      "0.00000999589592143481874284915305130",
      "0.00000999112305065851449336634665848",
      "0.00000998781448431307229896573490177",
      "0.00000999105586173337298647698954304",
      "0.00000999243989826367057452600019064",
      "0.00000999206211056412276207569552777",
      "0.00000999336007695975009614970150027",
      "0.00000999611275466518033112032701126",
      "0.00000999037569764779261024776324330",
      "0.00000998351572484655836370636209457",
      "0.00000999418160543864438551492377259",
      "0.00000998591737693908219662758156580",
      "0.00000998994135908134419817553955004",
      "0.00000999125299560256246165915693237",
      "0.00000997647606542529856466930967895",
      "0.00000999363031383774510244040652310",
      "0.00000999399505330697862567490994173",
      "0.00000998831579317172532393106940722",
      "0.00000999306741091049286753906057223",
      "0.00000999720710442410351158842994840",
      "0.00000999418464503767016301370676589",
      "0.00000998870699743322823341413720311",
      "0.00000999299186413079108290915762154",
      "0.00000998586535826423253082220826755",
      "0.00000997973899519023592535524805594",
      "0.00000999441302282142885446944797174",
      "0.00000999751771037333423625188462288",
      "0.00000998846593427626445567403596794",
      "0.00000999406683940283696133524771189",
      "0.00000999194099488671783439197343513",
      "0.00000998724793416528698309641822291",
      "0.00000998890512154266027803673423778",
      "0.00000999563101537844225104964859693",
      "0.00000999878199988902252742238225497",
      "0.00000999297772947864847384074328935",
      "0.00000998825392419491020185547477807",
      "0.00000999081043782214621298534033877",
      "0.00000999419949971685868552974838291",
      "0.00000999534029949177521963986302566",
      "0.00000999081043782214621298534033877",
      "0.00000999419200935177412335229023915",
      "0.00000999534029949177521963986302566",
      "0.00000999504237891773217129723071851",
      "0.00000999338521856878277642651448408",
      "0.00000999500797486668907904900717996",
      "0.00000999603780058323751528148435211",
      "0.00000999698086482075957980609722000",
      "0.00000999159765542317671041663925568",
      "0.00000999219724913705577653408763041",
      "0.00000999186440478751964131981399831",
      "0.00000999568086182707713953723096642",
      "0.00000999556910164827829683119636197",
      "0.00000999665959672766530680837389158",
      "0.00000999768473177663055770819591448",
      "0.00000999994226497308103742354908512"
    ],
    "containment_margins_hi_decimal": [
      "0.00000999243506262765675670627944816",
      "0.00000999459588489744174214350973536",
      "0.00000999022966941264804931800066641",
      "0.00000999577109549066259067988881324",
      "0.00000999848181037315688202311848722",
      "0.00000998535407396925329226796984757",
      "0.00000999535487620272129987200232439",
      "0.00000999442875558030770310231424826",
      "0.00000999509681120853336036396364242",
      "0.00000998799912686460467152298697949",
      "0.00000999257354576377857398361542275",
      "0.00000999794330169861528894529060230",
      "0.00000998788872316573337318622311471",
      "0.00000999509091777410622118380936568",
      "0.00000999434523858185992137557653064",
      "0.00000999607797118544081656105023429",
      "0.00000999549298220093621311741779040",
      "0.00000999530750348028723680827229547",
      "0.00000999215547760601954699979253682",
      "0.00000999374868604348588122741867528",
      "0.00000999021756744003800746604436440",
      "0.00000999645735280678346210720116315",
      "0.00000998440572909602240809009524186",
      "0.00000999248149129987819728969534563",
      "0.00000998930699743322823341413720311",
      "0.00000998759348818888445341791691587",
      "0.00000999607014256946129503287601458",
      "0.00000999428242690610263680254054229",
      "0.00000999437428110783531661004835260",
      "0.00000998840251491981811785971711925",
      "0.00000999336007695975009614970150027",
      "0.00000999608388715172084983210155382",
      "0.00000999037569764779261024776324330",
      "0.00000998695596743616600611398496791",
      "0.00000999292234306896453745667789955",
      "0.00000999704816220635727241777172445",
      "0.00000999620657817500772288220973804",
      "0.00000998786177817938431104344237576",
      "0.00000999259909821720620728893017688",
      "0.00000999200536521961939632119621056",
      "0.00000998808069976488918703308639969",
      "0.00000999929389249406780749955469226",
      "0.00000999545058435058204099954625378",
      "0.00000999637962954144195615036874409",
      "0.00000999196809577836545532502736311",
      "0.00000999287349256884004104060916769",
      "0.00000999372764825789003082285706272",
      "0.00000999834731055650166082097608901",
      "0.00000999940000000000000000000000000",
      "0.00000999391618750035103228845886569",
      "0.00000998293367763196578837145624383",
      "0.00000999940000000000000000000000000",
      "0.00000999391618750035103228845886569",
      "0.00000998293367763196578837145624383",
      "0.00000999610224255593294807470798795",
      "0.00000998788365583224381758382711287",
      "0.00000999294551304867523536926409863",
      "0.00000999647378501386151915096516157",
      "0.00000998201072529722616832325010030",
      "0.00000997970315352180336905106826654",
      "0.00000999247608509710058330162481412",
      "0.00000999638467536286425937383421724",
      "0.00000998724856323852428366783297175",
      "0.00000999589592143481874284915305130",
      "0.00000999112305065851449336634665848",
      "0.00000998781448431307229896573490177",
      "0.00000999105586173337298647698954304",
      "0.00000999243989826367057452600019064",
      "0.00000999206211056412276207569552777",
      "0.00000999336007695975009614970150027",
      "0.00000999611275466518033112032701126",
      "0.00000999037569764779261024776324330",
      "0.00000998351572484655836370636209457",
      "0.00000999418160543864438551492377259",
      "0.00000998591737693908219662758156580",
      "0.00000998994135908134419817553955004",
      "0.00000999125299560256246165915693237",
      "0.00000997647606542529856466930967895",
      "0.00000999363031383774510244040652310",
      "0.00000999399505330697862567490994173",
      "0.00000998831579317172532393106940722",
      "0.00000999306741091049286753906057223",
      "0.00000999720710442410351158842994840",
      "0.00000999418464503767016301370676589",
      "0.00000998870699743322823341413720311",
      "0.00000999299186413079108290915762154",
      "0.00000998586535826423253082220826755",
      "0.00000997973899519023592535524805594",
      "0.00000999441302282142885446944797174",
      "0.00000999751771037333423625188462288",
      "0.00000998846593427626445567403596794",
      "0.00000999406683940283696133524771189",
      "0.00000999194099488671783439197343513",
      "0.00000998724793416528698309641822291",
      "0.00000998890512154266027803673423778",
      "0.00000999563101537844225104964859693",
      "0.00000999878199988902252742238225497",
      "0.00000999297772947864847384074328935",
      "0.00000998825392419491020185547477807",
      "0.00000999081043782214621298534033877",
      "0.00000999419949971685868552974838291",
      "0.00000999534029949177521963986302566",
      "0.00000999081043782214621298534033877",
      "0.00000999419200935177412335229023915",
      "0.00000999534029949177521963986302566",
      "0.00000999504237891773217129723071851",
      "0.00000999338521856878277642651448408",
      "0.00000999500797486668907904900717996",
      "0.00000999603780058323751528148435211",
      "0.00000999698086482075957980609722000",
      "0.00000999159765542317671041663925568",
      "0.00000999219724913705577653408763041",
      "0.00000999186440478751964131981399831",
      "0.00000999568086182707713953723096642",
      "0.00000999556910164827829683119636197",
      "0.00000999665959672766530680837389158",
      "0.00000999768473177663055770819591448",
      "0.00000999994226497308103742354908512"
    ],
    "min_margin_decimal": "0.00000997647606542529856466930967895",
    "K_box_decimal": [
      [
        "-0.731642436639381406747234755768",
        "-0.731642421509506662060748168326"
      ],
      [
        "0.175035878262880969026525926050",
        "0.175035889071111174143041639031"
      ],
      [
        "-0.658833672698205690128713992875",
        "-0.658833653157544515424812628876"
      ],
      [
        "0.411106857676523570724808630441",
        "0.411106866134332589399627270664"
      ],
      [
        "-0.909562010753239687247710604951",
        "-0.909562007716860433561474651188"
      ],
      [
        "0.0607297099588339936327980428170",
        "0.0607297392506860551262135068773"
      ],
      [
        "0.320535562523892157063073383497",
        "0.320535571814139751620473639492"
      ],
      [
        "0.734526119996809569127511947843",
        "0.734526131139298408512105743215"
      ],
      [
        "0.598103933419926286930617899992",
        "0.598103943226303869863897172064"
      ],
      [
        "-0.0373235498731287744913992982385",
        "-0.0373235258713825037007423442124"
      ],
      [
        "-0.188881679800851642636293765878",
        "-0.188881664947943170193441733109"
      ],
      [
        "0.981290305325245168419880974110",
        "0.981290309438641771189303083529"
      ],
      [
        "-0.260171362604123740268235905080",
        "-0.260171338381570071734982277526"
      ],
      [
        "0.901474855948162422433962311605",
        "0.901474865766326874221519943987"
      ],
      [
        "-0.345910317188169757777844250117",
        "-0.345910305878646921497687001270"
      ],
      [
        "0.297494884443073730538496473579",
        "0.297494892287131359656863351479"
      ],
      [
        "-0.712593192989865040976660260884",
        "-0.712593183975829442849086495720"
      ],
      [
        "-0.635380000541031649879589594854",
        "-0.635379991156038610454063211399"
      ],
      [
        "0.777958712687942669989898678551",
        "0.777958728376987457950804678966"
      ],
      [
        "0.385805983863462856476227590465",
        "0.385805996366090769504465135628"
      ],
      [
        "0.495917288906619682047881407406",
        "0.495917308471484801971866475318"
      ],
      [
        "-0.903152619681764780453474217408",
        "-0.903152612596470394020398431811"
      ],
      [
        "-0.0256869037719221027732934215950",
        "-0.0256868725833802948181096017855"
      ],
      [
        "0.428550497949419270407334126049",
        "0.428550512986436670650939546658"
      ],
      [
        "0.125193884913649956494818059988",
        "0.125193906299655090038351231714"
      ],
      [
        "-0.360119114343637425310191433440",
        "-0.360119089530613803079098269273"
      ],
      [
        "-0.924467808086837643077715744839",
        "-0.924467800227122782000305810591"
      ],
      [
        "-0.883997214162942510265813939431",
        "-0.883997202727796322471087544512"
      ],
      [
        "-0.100358680431646299618410877186",
        "-0.100358669180208515289044097283"
      ],
      [
        "0.456592883498345562388362038062",
        "0.456592906693315722752126318628"
      ],
      [
        "0.846673663933190737022476070447",
        "0.846673677213036817522283771044"
      ],
      [
        "-0.0885230014845828472402904301580",
        "-0.0885229936523571506819900943611"
      ],
      [
        "0.524697402661810475026958098238",
        "0.524697421910415179441737602712"
      ],
      [
        "-0.106038500956936916232092949228",
        "-0.106038474868871788564105177197"
      ],
      [
        "0.285447308231192474501156332490",
        "0.285447322386506336572081419135"
      ],
      [
        "0.952510190833045090937390537478",
        "0.952510196736720678222845701935"
      ],
      [
        "0.818144745361289080682485173699",
        "0.818144752948132730667039409280"
      ],
      [
        "-0.177827430314470297898882900629",
        "-0.177827406038026656667504987514"
      ],
      [
        "0.546824076537749205259753865811",
        "0.546824091339552770847339287951"
      ],
      [
        "0.0580955380507929471230097008976",
        "0.0580955540400625078842170585051"
      ],
      [
        "0.00929967438630832959358999959999",
        "0.00929969822490879981521593342719"
      ],
      [
        "-0.998267711976135944317984303277",
        "-0.998267710563920932453599302386"
      ],
      [
        "-0.876240299749554282596334671645",
        "-0.876240290650722983760416670737"
      ],
      [
        "0.168527728250269454020747127926",
        "0.168527735491010371136834827189"
      ],
      [
        "0.451443619299473228697700550978",
        "0.451443635363281671966789900923"
      ],
      [
        "-0.0850078741109141127221329925110",
        "-0.0850078598578992504022150737293"
      ],
      [
        "-0.203514312626251418188864632904",
        "-0.203514300081547933968926278618"
      ],
      [
        "0.975374587753889515084344234210",
        "0.975374591059268402081022592258"
      ],
      [
        "0.499999999400000000000000000000",
        "0.500000000600000000000000000000"
      ],
      [
        "-0.815743403881839554713978738608",
        "-0.815743391714214555416043315526"
      ],
      [
        "-0.290796696808250970354010587320",
        "-0.290796662675606234285587330232"
      ],
      [
        "0.499999999400000000000000000000",
        "0.500000000600000000000000000000"
      ],
      [
        "0.815743391714214555416043315526",
        "0.815743403881839554713978738608"
      ],
      [
        "0.290796662675606234285587330232",
        "0.290796696808250970354010587320"
      ],
      [
        "0.930696257298271016302909322884",
        "0.930696265093785904437013173468"
      ],
      [
        "-0.159779429669086529726465841450",
        "-0.159779405436398194214101009104"
      ],
      [
        "0.329051671443344715229999786799",
        "0.329051685552318617879529048271"
      ],
      [
        "-0.430696264722243446508442097210",
        "-0.430696257669813474231480399141"
      ],
      [
        "-0.655963998234559395868559278540",
        "-0.655963962256009990320895925041"
      ],
      [
        "-0.619848378536606747071194325243",
        "-0.619848337942913790677932427379"
      ],
      [
        "0.554008847475638717646358500172",
        "0.554008862523468523445191896922"
      ],
      [
        "-0.683705598068599740227413620399",
        "-0.683705590837950465955932368067"
      ],
      [
        "-0.474995642936996771671350275850",
        "-0.474995617434123248719917611516"
      ],
      [
        "-0.495913313058204458223418969693",
        "-0.495913304850047327860904667999"
      ],
      [
        "0.693005271881934326310569327093",
        "0.693005289635833009281582594400"
      ],
      [
        "-0.523272093269984115117858893414",
        "-0.523272068898952741262456824884"
      ],
      [
        "0.670524901759043287741338633862",
        "0.670524919647319820995365679883"
      ],
      [
        "0.741695435744400550028032228519",
        "0.741695450864604022686883176519"
      ],
      [
        "-0.0168586409734661089602391324632",
        "-0.0168586250976872372057632838542"
      ],
      [
        "0.346673663933190737022476070447",
        "0.346673677213036817522283771044"
      ],
      [
        "0.777502402328723312982914028820",
        "0.777502410103213982622251788166"
      ],
      [
        "0.524697402661810475026958098238",
        "0.524697421910415179441737602712"
      ],
      [
        "-0.529746889534350303129981379723",
        "-0.529746856565799996246708792447"
      ],
      [
        "0.361506573016840346686487987436",
        "0.361506584653629469397716957589"
      ],
      [
        "0.767255643408745100000641769058",
        "0.767255671573991221836248513895"
      ],
      [
        "0.876420533564548008304923182370",
        "0.876420553681829845616526831291"
      ],
      [
        "0.415995818633729342322942095138",
        "0.415995836127738137198018776824"
      ],
      [
        "-0.242558268729189908385532621691",
        "-0.242558221681320758982661960311"
      ],
      [
        "-0.837680923357034549056988084853",
        "-0.837680910617662224547192965666"
      ],
      [
        "0.460483192970898784100028333263",
        "0.460483204980792170142776983443"
      ],
      [
        "0.293676519172800953528678739901",
        "0.293676542541214610078030877762"
      ],
      [
        "0.212487014448106774028373418469",
        "0.212487028313284953042638340348"
      ],
      [
        "-0.916107497629642493888257245634",
        "-0.916107492043851342095280422493"
      ],
      [
        "0.339994587742688866086020023815",
        "0.339994599373398790745693996401"
      ],
      [
        "0.625193884313649956494818059988",
        "0.625193906899655090038351231714"
      ],
      [
        "0.455624288852765571661449084868",
        "0.455624302869037310079283266553"
      ],
      [
        "-0.633671138549693345986680996731",
        "-0.633671110280409874451742641147"
      ],
      [
        "-0.118640031405651879390201780284",
        "-0.118639990883642259862052490780"
      ],
      [
        "-0.548055435986792330933635686109",
        "-0.548055424812837973791344625005"
      ],
      [
        "0.827985379613838558632187168208",
        "0.827985384578417811963714664439"
      ],
      [
        "0.551884888024468761006680695376",
        "0.551884911092600208477769347304"
      ],
      [
        "0.193640006971526536831928882210",
        "0.193640018837847731158006211715"
      ],
      [
        "0.811126741001546398932784100138",
        "0.811126757119556625497115316191"
      ],
      [
        "0.445724269675094631877746855073",
        "0.445724295179226301303780662237"
      ],
      [
        "-0.239968163959429410673969129075",
        "-0.239968141769672495994525202544"
      ],
      [
        "-0.862406607814000224116409617663",
        "-0.862406599076030981000911716961"
      ],
      [
        "0.997609180767694840355516202377",
        "0.997609183203695062310461357613"
      ],
      [
        "-0.0463281469821343406908057781038",
        "-0.0463281329375932979877534595904"
      ],
      [
        "-0.0512798661305398954335091036725",
        "-0.0512798426383882852539128146221"
      ],
      [
        "0.0442576725211083650508377082286",
        "0.0442576909002327207584117375479"
      ],
      [
        "-0.602902459439490462496612849179",
        "-0.602902447838489896213983908675"
      ],
      [
        "-0.796586402362851271463234106334",
        "-0.796586393043450255013673386060"
      ],
      [
        "-0.544257690900232720758411737548",
        "-0.544257672521108365050837708229"
      ],
      [
        "-0.263122955953439115634301439536",
        "-0.263122944337457819182548144116"
      ],
      [
        "0.796586393043450255013673386060",
        "0.796586402362851271463234106334"
      ],
      [
        "-0.831982618447089172541579651072",
        "-0.831982608531847008005922245533"
      ],
      [
        "-0.434374728383131697993730974855",
        "-0.434374715153568835559283827884"
      ],
      [
        "-0.345142775363798446217129471239",
        "-0.345142765379748179595287569253"
      ],
      [
        "-0.00975117725108249440363519417451",
        "-0.00975116932668366087866575714322"
      ],
      [
        "0.946828541579588391259677592156",
        "0.946828547617858749740517979962"
      ],
      [
        "-0.321590775919935329866109385874",
        "-0.321590759115246176219530219153"
      ],
      [
        "0.330286732655148169038700521241",
        "0.330286748260649894927147453066"
      ],
      [
        "-0.212302427166264794160647620716",
        "-0.212302410895074369199930260344"
      ],
      [
        "0.919694701521567658517216875773",
        "0.919694710159844004362937801311"
      ],
      [
        "0.501695868600670706569123792346",
        "0.501695877462467410012530129953"
      ],
      [
        "0.646677137458616576122103150274",
        "0.646677144139423120791489533526"
      ],
      [
        "-0.574551937784200741903311110100",
        "-0.574551933153664295164426526492"
      ],
      [
        "1.73205080751114226660848376505",
        "1.73205080762661232044640891796"
      ]
    ]
  },
  "verdict": {
    "certified": true,
    "method": "Krawczyk operator on square pinned system; mpmath.iv interval arithmetic",
    "criterion": "K(I) strictly inside int(I) componentwise",
    "reason": ""
  },
  "witness_source": {
    "numerical_certificate_path": "data/sweep_results/nontrivial_n28/nontrivial_snarks_n28_0225.json",
    "numerical_certificate_sha256": "22b16dfa50e4766357ccd8cd0f799c62e1ceb89fb8cb5d666b3c150b55641ad1"
  },
  "provenance": {
    "host": "MAC-02008878",
    "python": "3.12.4",
    "platform": "macOS-26.4.1-arm64-arm-64bit",
    "mpmath": "1.3.0",
    "sympy": "1.14.0",
    "numpy": "2.4.4",
    "schema_version": 2,
    "elapsed_seconds": 14.309520721435547,
    "timestamp_utc": "2026-05-14T07:08:08Z"
  }
}