{
  "schema_version": 2,
  "kind": "interval_witness",
  "name": "nontrivial_snarks_n28_1418",
  "graph": {
    "n": 28,
    "m": 42,
    "graph6": "[??G@eOGG??B_AO_g_??@_??O?HO????C??G@??WO?@???h?@???_C?g???O?O_@",
    "edges": [
      [
        0,
        8
      ],
      [
        0,
        12
      ],
      [
        0,
        16
      ],
      [
        1,
        13
      ],
      [
        1,
        14
      ],
      [
        1,
        26
      ],
      [
        2,
        7
      ],
      [
        2,
        9
      ],
      [
        2,
        18
      ],
      [
        3,
        7
      ],
      [
        3,
        8
      ],
      [
        3,
        17
      ],
      [
        4,
        5
      ],
      [
        4,
        18
      ],
      [
        4,
        22
      ],
      [
        5,
        14
      ],
      [
        5,
        21
      ],
      [
        6,
        7
      ],
      [
        6,
        13
      ],
      [
        6,
        25
      ],
      [
        8,
        9
      ],
      [
        9,
        11
      ],
      [
        10,
        11
      ],
      [
        10,
        12
      ],
      [
        10,
        27
      ],
      [
        11,
        24
      ],
      [
        12,
        13
      ],
      [
        14,
        15
      ],
      [
        15,
        25
      ],
      [
        15,
        27
      ],
      [
        16,
        17
      ],
      [
        16,
        20
      ],
      [
        17,
        23
      ],
      [
        18,
        19
      ],
      [
        19,
        21
      ],
      [
        19,
        23
      ],
      [
        20,
        21
      ],
      [
        20,
        22
      ],
      [
        22,
        23
      ],
      [
        24,
        25
      ],
      [
        24,
        26
      ],
      [
        26,
        27
      ]
    ],
    "orientation": "lex (u,v) with u<v points u->v"
  },
  "pinning": {
    "pinned_vertex": 0,
    "pinned_edge_indices": [
      0,
      1,
      2
    ],
    "pinned_signs": [
      1,
      1,
      1
    ],
    "target_labels": [
      "(1,0,0)",
      "(-1/2, s/2, 0)",
      "(-1/2, -s/2, 0)"
    ],
    "dropped_redundant_vertex": 27
  },
  "system": {
    "free_vars": [
      "x_3_0",
      "x_3_1",
      "x_3_2",
      "x_4_0",
      "x_4_1",
      "x_4_2",
      "x_5_0",
      "x_5_1",
      "x_5_2",
      "x_6_0",
      "x_6_1",
      "x_6_2",
      "x_7_0",
      "x_7_1",
      "x_7_2",
      "x_8_0",
      "x_8_1",
      "x_8_2",
      "x_9_0",
      "x_9_1",
      "x_9_2",
      "x_10_0",
      "x_10_1",
      "x_10_2",
      "x_11_0",
      "x_11_1",
      "x_11_2",
      "x_12_0",
      "x_12_1",
      "x_12_2",
      "x_13_0",
      "x_13_1",
      "x_13_2",
      "x_14_0",
      "x_14_1",
      "x_14_2",
      "x_15_0",
      "x_15_1",
      "x_15_2",
      "x_16_0",
      "x_16_1",
      "x_16_2",
      "x_17_0",
      "x_17_1",
      "x_17_2",
      "x_18_0",
      "x_18_1",
      "x_18_2",
      "x_19_0",
      "x_19_1",
      "x_19_2",
      "x_20_0",
      "x_20_1",
      "x_20_2",
      "x_21_0",
      "x_21_1",
      "x_21_2",
      "x_22_0",
      "x_22_1",
      "x_22_2",
      "x_23_0",
      "x_23_1",
      "x_23_2",
      "x_24_0",
      "x_24_1",
      "x_24_2",
      "x_25_0",
      "x_25_1",
      "x_25_2",
      "x_26_0",
      "x_26_1",
      "x_26_2",
      "x_27_0",
      "x_27_1",
      "x_27_2",
      "x_28_0",
      "x_28_1",
      "x_28_2",
      "x_29_0",
      "x_29_1",
      "x_29_2",
      "x_30_0",
      "x_30_1",
      "x_30_2",
      "x_31_0",
      "x_31_1",
      "x_31_2",
      "x_32_0",
      "x_32_1",
      "x_32_2",
      "x_33_0",
      "x_33_1",
      "x_33_2",
      "x_34_0",
      "x_34_1",
      "x_34_2",
      "x_35_0",
      "x_35_1",
      "x_35_2",
      "x_36_0",
      "x_36_1",
      "x_36_2",
      "x_37_0",
      "x_37_1",
      "x_37_2",
      "x_38_0",
      "x_38_1",
      "x_38_2",
      "x_39_0",
      "x_39_1",
      "x_39_2",
      "x_40_0",
      "x_40_1",
      "x_40_2",
      "x_41_0",
      "x_41_1",
      "x_41_2",
      "s"
    ],
    "n_free_vars": 118,
    "n_polynomials": 118,
    "polynomial_hash_sha256": "0c11259c915cce7d37a7ff102cc551d7d724d8da90ab938dec51632ed7747470",
    "polynomial_hash_canonicalization": "sympy.expand then sympy.srepr per poly, joined"
  },
  "krawczyk": {
    "radius_decimal": "1e-05",
    "dps": 50,
    "center_decimal": [
      "-0.90616216882174046233701273501644810104290295296307",
      "-0.17870757409732662040680843973367369102353215452671",
      "-0.38331935348548219775545523431161889928458950969256",
      "0.78126844329147219295862507334585183513190908204196",
      "-0.55626474474080758423071497593644457353870197414033",
      "-0.28317689396446857566195045342011149264869534683366",
      "0.12489372553026826937838766167059626591099387092111",
      "0.73497231883813420463752341567011826456223412866704",
      "0.66649624744995077341740568773173039193328485652622",
      "0.25086818611484343609717959620627870052965128544213",
      "-0.96139784323288950160122190893383669205825059090928",
      "0.11304574393844598413122151462917684496202464874692",
      "0.47880041752153110671765545479406888525415676448979",
      "0.56611317951319718158840917381754934087080052804342",
      "-0.67101864963849258939261025732356951788129978464692",
      "-0.72966860363637454281483505100034758578380804993192",
      "0.39528466371969232001281273511628735118745006286586",
      "0.55797290570004660526138874269439267291927513590000",
      "-0.35382347368782070006648564834332791252263945649882",
      "0.32460631104850998149222519293840680720063835081412",
      "-0.87717711569269865411921313332035535622642798692510",
      "-0.50000000000000000000000000000000000000000000000000",
      "-0.69723529015335638206755337993478334264505083475137",
      "0.51367591939350722977262159655299131657203787440889",
      "0.85382347368782070006648564834332791252263945649882",
      "0.37262897910484640057532818699637653544441248393726",
      "0.36350119629919142434659153676736403965439011251621",
      "-0.97880041752153110671765545479406888525415676448979",
      "0.13112211064015920047914420611723400177425030670795",
      "0.15734273024498535961998866077057820130926191023802",
      "0.47880041752153110671765545479406888525415676448979",
      "0.56611317951319718158840917381754934087080052804342",
      "-0.67101864963849258939261025732356951788129978464692",
      "0.50000000000000000000000000000000000000000000000000",
      "-0.69723529015335638206755337993478334264505083475137",
      "0.51367591939350722977262159655299131657203787440890",
      "-0.37584512994855384274834940265701967326116859343311",
      "-0.098111760959899926175582248640272296839540080102075",
      "0.92147410199923802960798027946175671257366524841621",
      "-0.60295528757297726396930605213704921199298817105669",
      "0.22923387160005912665472645475750629861379038681002",
      "-0.76413137175425266998799161869117851126440333817819",
      "0.10295528757297726396930605213704921199298817105669",
      "0.63679153218437952010899671599542988485761224009516",
      "0.76413137175425266998799161869117851126440333817818",
      "0.80320688124876319836770668287939888904991478190638",
      "-0.45808395808705289970218827626175619383408008556845",
      "-0.38081201826877047223253638437955961197981382848562",
      "-0.90616216882174046233701273501644810104290295296307",
      "-0.17870757409732662040680843973367369102353215452671",
      "-0.38331935348548219775545523431161889928458950969256",
      "0.50000000000000000000000000000000000000000000000000",
      "-0.69723529015335638206755337993478334264505083475137",
      "0.51367591939350722977262159655299131657203787440889",
      "0.97880041752153110671765545479406888525415676448979",
      "-0.13112211064015920047914420611723400177425030670795",
      "-0.15734273024498535961998866077057820130926191023802",
      "-0.39878210041930540170639411376138654897429550392609",
      "0.91472070134424365861127143144037881285765132089658",
      "-0.065260056063889647861662574563496228556133847422447",
      "0.60295528757297726396930605213704921199298817105669",
      "-0.22923387160005912665472645475750629861379038681003",
      "0.76413137175425266998799161869117851126440333817818",
      "-0.20417318715367186226291193837566266301869266713060",
      "-0.68548682974418453195654497668287251424386093408655",
      "-0.69887131569036302212632904412768228270826949075574",
      "0.58001831710222570501126134103268233627986126056371",
      "0.78359859070408445813212722532314481108340101418863",
      "-0.22260278630887500748165123533407442986539575766047",
      "0.10295528757297726396930605213704921199298817105669",
      "0.63679153218437952010899671599542988485761224009516",
      "0.76413137175425266998799161869117851126440333817818",
      "0.40542331334291835021027567068883216187074048860885",
      "-0.65437650570070751040629722457671687037824205424241",
      "0.63829720803476945394602982604164521992496990158255",
      "0.78126844329147219295862507334585183513190908204196",
      "-0.55626474474080758423071497593644457353870197414033",
      "-0.28317689396446857566195045342011149264869534683366",
      "-0.37584512994855384274834940265701967326116859343311",
      "-0.098111760959899926175582248640272296839540080102074",
      "0.92147410199923802960798027946175671257366524841621",
      "0.015066415842419934687085552801487151302022531624287",
      "-0.58604886843196975603423168621448194669081162125551",
      "-0.81013562254925630467667297884660768424805609638723",
      "-0.51506641584241993468708555280148715130202253162429",
      "-0.27997653535246889072949148453845423678059100564968",
      "0.81013562254925630467667297884660768424805609638723",
      "0.86888988953024063475357120114481506382466198812310",
      "-0.21341988932712335545890349921810541124639913731825",
      "-0.44663442625006488033008144207924364459366598387102",
      "-0.25086818611484343609717959620627870052965128544213",
      "0.96139784323288950160122190893383669205825059090928",
      "-0.11304574393844598413122151462917684496202464874692",
      "0.54668672819397423737072344972636811728333509312159",
      "0.71413690692530261849820340636643880004534768840631",
      "0.43719800935471949909469989213615072007077121576687",
      "-0.79755491430881767346790304593264681781298637856372",
      "0.24726093630758688310301850256739789201290290250297",
      "-0.55024375329316548322592140676532756503279586451379",
      "0.056268559379003026598582602410681094709653077935096",
      "-0.94337077852536174515292986112394509865913807521633",
      "0.32693336239953317089329172655502779119363212241132",
      "-0.57133497522142296128566815521216824601167560955938",
      "0.66339424317289285442343837658549086187854706956665",
      "0.48320226014972313378338125229157989305442397397592",
      "-0.071334975221422961285668155212168246011675609559378",
      "-0.033841046980463527644115003349292480766503765184717",
      "0.99687817954323036355600284884457120962646184838482",
      "0.12489372553026826937838766167059626591099387092111",
      "0.73497231883813420463752341567011826456223412866704",
      "0.66649624744995077341740568773173039193328485652622",
      "0.45512459157195743563287367936208607036886738964260",
      "0.048626271865950253494603809653026546521166885521582",
      "-0.88909903375882578089905692306580482179868061418669",
      "0.58001831710222570501126134103268233627986126056371",
      "0.78359859070408445813212722532314481108340101418862",
      "-0.22260278630887500748165123533407442986539575766047",
      "1.7320508075688772935274463415058723669428052538104"
    ],
    "F_residual_at_center_decimal": "2.67276471009219564614053646715e-51",
    "containment_margins_lo_decimal": [
      "0.00000999329278561975866168935795296",
      "0.00000998765938228374525114966299385",
      "0.00000997816756386906304470947836611",
      "0.00000999517670507717484002611091234",
      "0.00000999477641891805153855379411221",
      "0.00000999494039411150786873669390830",
      "0.00000998946156464184789834020240721",
      "0.00000998579844370303408961853639856",
      "0.00000998228468488695624090025857115",
      "0.00000998899359890644227425812655131",
      "0.00000999728235472330370769370859304",
      "0.00000999570374988126047143921019786",
      "0.00000999607206869722746392128306105",
      "0.00000998777995477900038150866808162",
      "0.00000998697899977572420652419313661",
      "0.00000998582142155053519672655987787",
      "0.00000998521547029444271356937184171",
      "0.00000999113387260312787367017925376",
      "0.00000999736687604148956112759443196",
      "0.00000999645989591932120492458974408",
      "0.00000999766339324653144162813616368",
      "0.00000999940000000000000000000000000",
      "0.00000999810238178296203846987858516",
      "0.00000999800779890260890549361231820",
      "0.00000999796687604148956112759443196",
      "0.00000999721625937275742797025879933",
      "0.00000999773954829791619211653548478",
      "0.00000999401441660377781673877849966",
      "0.00000997615675886054095650727598516",
      "0.00000998263908353067719232371034180",
      "0.00000998563802314633134869678677856",
      "0.00000998491331442620170897630939077",
      "0.00000997859702607630349304919152605",
      "0.00000998613377805945533235565061965",
      "0.00000998208312313505788318411510283",
      "0.00000998623010662955405898121707641",
      "0.00000998488722185931404525417078628",
      "0.00000998609226192733684588979374947",
      "0.00000999208801543697797947618894003",
      "0.00000998801442158358840683605638300",
      "0.00000998424427978124975036845573726",
      "0.00000999029044132991109717326589394",
      "0.00000998856965121506551873500679123",
      "0.00000999700819044410845115621505739",
      "0.00000999579823019354889463152812477",
      "0.00000999505859278452566665504991500",
      "0.00000999276420901333392065884126784",
      "0.00000998446587394368874458625245780",
      "0.00000999283451611578064636029143176",
      "0.00000999056205031050227548231752068",
      "0.00000998033695463797940077987192321",
      "0.00000999940000000000000000000000000",
      "0.00000999810238178296203846987858516",
      "0.00000999800779890260890549361231820",
      "0.00000999627400058599902916500734303",
      "0.00000998831392069580126685553684376",
      "0.00000998788624563052687410771706480",
      "0.00000999186198153482097996692274345",
      "0.00000999690724337666818649628176431",
      "0.00000999172281697591009867974458077",
      "0.00000998902792071904353406407331243",
      "0.00000999367600309936447891001389174",
      "0.00000999362883942463253856113456767",
      "0.00000998161767671922850074699146025",
      "0.00000999095939513164850256752897927",
      "0.00000998564969860537780226279866934",
      "0.00000999489375377685988313907374374",
      "0.00000999077551959050673760484048048",
      "0.00000997996191603150186929634682176",
      "0.00000998902792071904353406407331243",
      "0.00000999365762594451653358847520466",
      "0.00000999362883942463253856113456767",
      "0.00000998736435942319459190682106364",
      "0.00000998804269251865155864646455822",
      "0.00000999469429411006702796303234848",
      "0.00000999407095167489899329032788247",
      "0.00000999361958779354339564117478773",
      "0.00000999455351660867848421977049400",
      "0.00000998278138601590601647687500447",
      "0.00000998400725520950035758298701033",
      "0.00000999170113793414859495926552573",
      "0.00000999559829547228477848076674145",
      "0.00000999692383656738698676735804782",
      "0.00000999770269569324737195940365328",
      "0.00000999559829547228477848076674145",
      "0.00000999692613939515894272672535489",
      "0.00000999770269569324737195940365328",
      "0.00000999741202867595448643580802146",
      "0.00000999754149171327270794186468365",
      "0.00000999554562656886261099879667169",
      "0.00000998380650721867457091855176402",
      "0.00000999535945589926662056961842846",
      "0.00000998529058119807847108707886378",
      "0.00000998586819301650452498456846974",
      "0.00000998818149362245081196472633794",
      "0.00000998627702598250883889153156778",
      "0.00000999562587429456418580227631128",
      "0.00000998391209095707045011443625814",
      "0.00000999497435995626253255985534751",
      "0.00000998843156670906620073641117295",
      "0.00000999561756267695486121508799338",
      "0.00000998867395432985553492067368778",
      "0.00000998743004382216136862998727836",
      "0.00000999589980829289648845112080431",
      "0.00000998699031241848921229763671103",
      "0.00000999449916726344539835257428484",
      "0.00000998344496131344775377393267220",
      "0.00000999893789142706983182397332798",
      "0.00000998751653694074155436297220342",
      "0.00000998743580187303590098780747671",
      "0.00000998465182935799483535152562730",
      "0.00000999032119558276199067227604006",
      "0.00000997847119970776892810814964416",
      "0.00000999370048716189487141603053674",
      "0.00000999461391453392327338044409949",
      "0.00000999209850507729846043652832143",
      "0.00000997740564775975612870902985036",
      "0.00000999994226497308103742354908512"
    ],
    "containment_margins_hi_decimal": [
      "0.00000999329278561975866168935795296",
      "0.00000998765938228374525114966299385",
      "0.00000997816756386906304470947836611",
      "0.00000999517670507717484002611091234",
      "0.00000999477641891805153855379411221",
      "0.00000999494039411150786873669390830",
      "0.00000998946156464184789834020240721",
      "0.00000998579844370303408961853639856",
      "0.00000998228468488695624090025857115",
      "0.00000998899359890644227425812655131",
      "0.00000999728235472330370769370859304",
      "0.00000999570374988126047143921019786",
      "0.00000999607206869722746392128306105",
      "0.00000998777995477900038150866808162",
      "0.00000998697899977572420652419313661",
      "0.00000998582142155053519672655987787",
      "0.00000998521547029444271356937184171",
      "0.00000999113387260312787367017925376",
      "0.00000999736687604148956112759443196",
      "0.00000999645989591932120492458974408",
      "0.00000999766339324653144162813616368",
      "0.00000999940000000000000000000000000",
      "0.00000999810238178296203846987858516",
      "0.00000999800779890260890549361231820",
      "0.00000999796687604148956112759443196",
      "0.00000999721625937275742797025879933",
      "0.00000999773954829791619211653548478",
      "0.00000999401441660377781673877849966",
      "0.00000997615675886054095650727598516",
      "0.00000998263908353067719232371034180",
      "0.00000998563802314633134869678677856",
      "0.00000998491331442620170897630939077",
      "0.00000997859702607630349304919152605",
      "0.00000998613377805945533235565061965",
      "0.00000998208312313505788318411510283",
      "0.00000998623010662955405898121707641",
      "0.00000998488722185931404525417078628",
      "0.00000998609226192733684588979374947",
      "0.00000999208801543697797947618894003",
      "0.00000998801442158358840683605638300",
      "0.00000998424427978124975036845573726",
      "0.00000999029044132991109717326589394",
      "0.00000998856965121506551873500679123",
      "0.00000999700819044410845115621505739",
      "0.00000999579823019354889463152812477",
      "0.00000999505859278452566665504991500",
      "0.00000999276420901333392065884126784",
      "0.00000998446587394368874458625245780",
      "0.00000999283451611578064636029143176",
      "0.00000999056205031050227548231752068",
      "0.00000998033695463797940077987192321",
      "0.00000999940000000000000000000000000",
      "0.00000999810238178296203846987858516",
      "0.00000999800779890260890549361231820",
      "0.00000999627400058599902916500734303",
      "0.00000998831392069580126685553684376",
      "0.00000998788624563052687410771706480",
      "0.00000999186198153482097996692274345",
      "0.00000999690724337666818649628176431",
      "0.00000999172281697591009867974458077",
      "0.00000998902792071904353406407331243",
      "0.00000999367600309936447891001389174",
      "0.00000999362883942463253856113456767",
      "0.00000998161767671922850074699146025",
      "0.00000999095939513164850256752897927",
      "0.00000998564969860537780226279866934",
      "0.00000999489375377685988313907374374",
      "0.00000999077551959050673760484048048",
      "0.00000997996191603150186929634682176",
      "0.00000998902792071904353406407331243",
      "0.00000999365762594451653358847520466",
      "0.00000999362883942463253856113456767",
      "0.00000998736435942319459190682106364",
      "0.00000998804269251865155864646455822",
      "0.00000999469429411006702796303234848",
      "0.00000999407095167489899329032788247",
      "0.00000999361958779354339564117478773",
      "0.00000999455351660867848421977049400",
      "0.00000998278138601590601647687500447",
      "0.00000998400725520950035758298701033",
      "0.00000999170113793414859495926552573",
      "0.00000999559829547228477848076674145",
      "0.00000999692383656738698676735804782",
      "0.00000999770269569324737195940365328",
      "0.00000999559829547228477848076674145",
      "0.00000999692613939515894272672535489",
      "0.00000999770269569324737195940365328",
      "0.00000999741202867595448643580802146",
      "0.00000999754149171327270794186468365",
      "0.00000999554562656886261099879667169",
      "0.00000998380650721867457091855176402",
      "0.00000999535945589926662056961842846",
      "0.00000998529058119807847108707886378",
      "0.00000998586819301650452498456846974",
      "0.00000998818149362245081196472633794",
      "0.00000998627702598250883889153156778",
      "0.00000999562587429456418580227631128",
      "0.00000998391209095707045011443625814",
      "0.00000999497435995626253255985534751",
      "0.00000998843156670906620073641117295",
      "0.00000999561756267695486121508799338",
      "0.00000998867395432985553492067368778",
      "0.00000998743004382216136862998727836",
      "0.00000999589980829289648845112080431",
      "0.00000998699031241848921229763671103",
      "0.00000999449916726344539835257428484",
      "0.00000998344496131344775377393267220",
      "0.00000999893789142706983182397332798",
      "0.00000998751653694074155436297220342",
      "0.00000998743580187303590098780747671",
      "0.00000998465182935799483535152562730",
      "0.00000999032119558276199067227604006",
      "0.00000997847119970776892810814964416",
      "0.00000999370048716189487141603053674",
      "0.00000999461391453392327338044409949",
      "0.00000999209850507729846043652832143",
      "0.00000997740564775975612870902985036",
      "0.00000999994226497308103742354908512"
    ],
    "min_margin_decimal": "0.00000997615675886054095650727598516",
    "K_box_decimal": [
      [
        "-0.906162175528954842578351045658",
        "-0.906162162114526082095674424374"
      ],
      [
        "-0.178707586437944336661557290071",
        "-0.178707561756708904152059589397"
      ],
      [
        "-0.383319375317918328692410524833",
        "-0.383319331653046066818499943790"
      ],
      [
        "0.781268438468177270133465099457",
        "0.781268448114767115783785047235"
      ],
      [
        "-0.556264749964388666179176422142",
        "-0.556264739517226502282253529731"
      ],
      [
        "-0.283176899024074464154081716726",
        "-0.283176888904862687169819190114"
      ],
      [
        "0.124893714991832911226286001873",
        "0.124893736068703627530489321468"
      ],
      [
        "0.734972304636577907671613034207",
        "0.734972333039690501603433797134"
      ],
      [
        "0.666496229734635660373646587990",
        "0.666496265165265886461164787473"
      ],
      [
        "0.250868175108442342539453854333",
        "0.250868197121244529654905338080"
      ],
      [
        "-0.961397845950534778297514215225",
        "-0.961397840515244224904929602642"
      ],
      [
        "0.113045739642195865391692953839",
        "0.113045748234696102870750075419"
      ],
      [
        "0.478800413593599803945119376077",
        "0.478800421449462409490191533511"
      ],
      [
        "0.566113167293151960588790682486",
        "0.566113191733242402588027665149"
      ],
      [
        "-0.671018662659492813668403733130",
        "-0.671018636617492365116816781517"
      ],
      [
        "-0.729668617814952992279638324440",
        "-0.729668589457796093350031777560"
      ],
      [
        "0.395284648935162614455526304488",
        "0.395284678504222025570099165744"
      ],
      [
        "0.557972896833919208389262412874",
        "0.557972914566174002133515072515"
      ],
      [
        "-0.353823476320944658576924520749",
        "-0.353823471054696741556046775938"
      ],
      [
        "0.324606307508405900813430117528",
        "0.324606314588614062171020268349"
      ],
      [
        "-0.877177118029305407587771505184",
        "-0.877177113356091900650654761457"
      ],
      [
        "-0.500000000600000000000000000000",
        "-0.499999999400000000000000000000"
      ],
      [
        "-0.697235292050974599105514910056",
        "-0.697235288255738165029591849813"
      ],
      [
        "0.513675917401306132381527090165",
        "0.513675921385708327163716102941"
      ],
      [
        "0.853823471654696741556046775938",
        "0.853823475720944658576924520749"
      ],
      [
        "0.372628976321105773332756157255",
        "0.372628981888587027817900216738"
      ],
      [
        "0.363501194038739722262783653303",
        "0.363501198559643126430399420232"
      ],
      [
        "-0.978800423507114502939838716016",
        "-0.978800411535947710495472193573"
      ],
      [
        "0.131122086796918061020100713393",
        "0.131122134483400339938187698841"
      ],
      [
        "0.157342712884068890297180984481",
        "0.157342747605901828942796337060"
      ],
      [
        "0.478800403159554253049004151581",
        "0.478800431883507960386306758007"
      ],
      [
        "0.566113164426511607790118150127",
        "0.566113194599882755386700197508"
      ],
      [
        "-0.671018671041466513089117208132",
        "-0.671018628235518665696103306515"
      ],
      [
        "0.499999986133778059455332355651",
        "0.500000013866221940544667644349"
      ],
      [
        "-0.697235308070233247009670195820",
        "-0.697235272236479517125436564050"
      ],
      [
        "0.513675905623613859326680577770",
        "0.513675933163400600218562615336"
      ],
      [
        "-0.375845145061331983434304148486",
        "-0.375845114835775702062394656828"
      ],
      [
        "-0.0981117748676379988387363588465",
        "-0.0981117470521618535124281384340"
      ],
      [
        "0.921474094087253466585959755651",
        "0.921474109911222592630000803273"
      ],
      [
        "-0.602955299558555680380899216081",
        "-0.602955275587398847557712888193"
      ],
      [
        "0.229233855844338907904476823213",
        "0.229233887355779345404976086302"
      ],
      [
        "-0.764131381463811340076894445425",
        "-0.764131362044693999899088791957"
      ],
      [
        "0.102955276142628479034824787144",
        "0.102955299003326048903787317130"
      ],
      [
        "0.636791529192569964217447872210",
        "0.636791535176189076000545559780"
      ],
      [
        "0.764131367552482863536886250219",
        "0.764131375956022476439096987163"
      ],
      [
        "0.803206876307355982893373337929",
        "0.803206886190170413842040027829"
      ],
      [
        "-0.458083965322843886368267617420",
        "-0.458083950851261913036108935103"
      ],
      [
        "-0.380812033802896528543791798127",
        "-0.380812002734644415921280970632"
      ],
      [
        "-0.906162175987224346556366374725",
        "-0.906162161656256578117659095308"
      ],
      [
        "-0.178707583535276309904532957416",
        "-0.178707564659376930909083922051"
      ],
      [
        "-0.383319373148527559776054454440",
        "-0.383319333822436835734856014184"
      ],
      [
        "0.499999999400000000000000000000",
        "0.500000000600000000000000000000"
      ],
      [
        "-0.697235292050974599105514910056",
        "-0.697235288255738165029591849813"
      ],
      [
        "0.513675917401306132381527090165",
        "0.513675921385708327163716102941"
      ],
      [
        "0.978800413795531692716684619801",
        "0.978800421247530520718626289787"
      ],
      [
        "-0.131122122326238504677877350580",
        "-0.131122098954079896280411061654"
      ],
      [
        "-0.157342742358739729093114553054",
        "-0.157342718131230990146862768488"
      ],
      [
        "-0.398782108557323866885414146839",
        "-0.398782092281286936527374080684"
      ],
      [
        "0.914720698251487035279457927722",
        "0.914720704437000281943084935159"
      ],
      [
        "-0.0652600643410726719515638948189",
        "-0.0652600477867066237717612543081"
      ],
      [
        "0.602955276600897983012840116210",
        "0.602955298545056544925771988064"
      ],
      [
        "-0.229233877924056027290247544744",
        "-0.229233865276062226019205364771"
      ],
      [
        "0.764131365383092094620530179826",
        "0.764131378125413245355453057557"
      ],
      [
        "-0.204173205535995143034411191384",
        "-0.204173168771348581491412685367"
      ],
      [
        "-0.685486838784789400308042409154",
        "-0.685486820703579663605047544212"
      ],
      [
        "-0.698871330040664416748526781329",
        "-0.698871301340061627504131306926"
      ],
      [
        "0.580018311995979481871144480106",
        "0.580018322208471928151378201959"
      ],
      [
        "0.783598581479604048638864830164",
        "0.783598599928564867625389620483"
      ],
      [
        "-0.222602806346958975979781938987",
        "-0.222602766270791038983520531681"
      ],
      [
        "0.102955276600897983012840116210",
        "0.102955298545056544925771988064"
      ],
      [
        "0.636791525842005464625530304471",
        "0.636791538526753575592463127520"
      ],
      [
        "0.764131365383092094620530179826",
        "0.764131378125413245355453057557"
      ],
      [
        "0.405423300707277773404867577510",
        "0.405423325978558927015683763868"
      ],
      [
        "-0.654376517658014991754738578112",
        "-0.654376493743400029057855871041"
      ],
      [
        "0.638297202729063564013057789074",
        "0.638297213340475343879001863009"
      ],
      [
        "0.781268437362423867857618363674",
        "0.781268449220520518059631783018"
      ],
      [
        "-0.556264751121219790687319334762",
        "-0.556264738360395377774110617111"
      ],
      [
        "-0.283176899410951966983466233650",
        "-0.283176888517985184340434673191"
      ],
      [
        "-0.375845147167167826842332925782",
        "-0.375845112729939858654365879532"
      ],
      [
        "-0.0981117769526447166752246656533",
        "-0.0981117449671551356759398316273"
      ],
      [
        "0.921474093700375963756575238727",
        "0.921474110298100095459385320196"
      ],
      [
        "0.0150664114407154069718640335682",
        "0.0150664202441244624023070720347"
      ],
      [
        "-0.586048871508133188647244918856",
        "-0.586048865355806323421218453573"
      ],
      [
        "-0.810135624846560611429301019443",
        "-0.810135620251951997924044938250"
      ],
      [
        "-0.515066420244124462402307072035",
        "-0.515066411440715406971864033568"
      ],
      [
        "-0.279976538426329495570548757813",
        "-0.279976532278608285888434211264"
      ],
      [
        "0.810135620251951997924044938250",
        "0.810135624846560611429301019443"
      ],
      [
        "0.868889886942269310708057636953",
        "0.868889892118211958799084765337"
      ],
      [
        "-0.213419891785631642186195557353",
        "-0.213419886868615068731611441083"
      ],
      [
        "-0.446634430704438311467470443283",
        "-0.446634421795691449192692440876"
      ],
      [
        "-0.250868202308336217422608677655",
        "-0.250868169921350654771750514758"
      ],
      [
        "0.961397838592345400867842478552",
        "0.961397847873433602334601339315"
      ],
      [
        "-0.113045758647864786052750427550",
        "-0.113045729229027182209692601708"
      ],
      [
        "0.546686714062167253875248434295",
        "0.546686742325781220866198465158"
      ],
      [
        "0.714136895106796240949015371093",
        "0.714136918743808996047391441640"
      ],
      [
        "0.437197995631745481603538783668",
        "0.437198023077693516585861000605"
      ],
      [
        "-0.797554918682943378903717243656",
        "-0.797554909934691968032088848209"
      ],
      [
        "0.247260920219677840173468617004",
        "0.247260952395495926032568388131"
      ],
      [
        "-0.550243758318805526963388846910",
        "-0.550243748267525439488453966621"
      ],
      [
        "0.0562685478105697356647833388219",
        "0.0562685709474363175323818659995"
      ],
      [
        "-0.943370782907799068198068646036",
        "-0.943370774142924422107791076212"
      ],
      [
        "0.326933351073487500748826647229",
        "0.326933373725578841037756805881"
      ],
      [
        "-0.571334987791379139124299525225",
        "-0.571334962651466783447036785199"
      ],
      [
        "0.663394239072701147319926827706",
        "0.663394247273084561526949925465"
      ],
      [
        "0.483202247140035552272593549928",
        "0.483202273159410715294168954655"
      ],
      [
        "-0.0713349807222556978402698026379",
        "-0.0713349697205902247310665077865"
      ],
      [
        "-0.0338410635355022141963612294166",
        "-0.0338410304254248410918687772820"
      ],
      [
        "0.996878178481121790625834672818",
        "0.996878180605338936486171024871"
      ],
      [
        "0.124893713046805210119942024643",
        "0.124893738013731328636833298698"
      ],
      [
        "0.734972306273936077673424403478",
        "0.734972331402332331601622427863"
      ],
      [
        "0.666496232101780131412241039257",
        "0.666496262798121415422570336206"
      ],
      [
        "0.455124581893153018394864351638",
        "0.455124601250761852870883007086"
      ],
      [
        "0.0486262503371499612635319178027",
        "0.0486262933947505457256757015034"
      ],
      [
        "-0.889099040058338619004185507035",
        "-0.889099027459312942793928339096"
      ],
      [
        "0.580018311716140238934534721477",
        "0.580018322488311171087987960589"
      ],
      [
        "0.783598582802589535430587661851",
        "0.783598598605579380833666788795"
      ],
      [
        "-0.222602808903227247725522526304",
        "-0.222602763714522767237779944364"
      ],
      [
        "1.73205080751114226660848376505",
        "1.73205080762661232044640891796"
      ]
    ]
  },
  "verdict": {
    "certified": true,
    "method": "Krawczyk operator on square pinned system; mpmath.iv interval arithmetic",
    "criterion": "K(I) strictly inside int(I) componentwise",
    "reason": ""
  },
  "witness_source": {
    "numerical_certificate_path": "data/sweep_results/nontrivial_n28/nontrivial_snarks_n28_1418.json",
    "numerical_certificate_sha256": "f28a1f4201c2f4d7105ce51334e2ba453d066ec0188e6e2a997df2640da36af1"
  },
  "provenance": {
    "host": "MAC-02008878",
    "python": "3.12.4",
    "platform": "macOS-26.4.1-arm64-arm-64bit",
    "mpmath": "1.3.0",
    "sympy": "1.14.0",
    "numpy": "2.4.4",
    "schema_version": 2,
    "elapsed_seconds": 14.333456993103027,
    "timestamp_utc": "2026-05-14T08:08:41Z"
  }
}